qiyu_sso/__init__.py
qiyu_sso/api/__init__.py
qiyu_sso/api/async_api.py
qiyu_sso/api/async_api_test.py
qiyu_sso/api/base.py
qiyu_sso/api/base_test.py
qiyu_sso/api/sync_api.py
qiyu_sso/api/sync_api_test.py
qiyu_sso/api/test_helper.py
qiyu_sso/forms/__init__.py
qiyu_sso/forms/client_base.py
qiyu_sso/forms/login.py
qiyu_sso/forms/sms_send.py
qiyu_sso/forms/token.py
qiyu_sso/forms/user_info.py
qiyu_sso/helper/__init__.py
qiyu_sso/resp/__init__.py
qiyu_sso/resp/token.py
qiyu_sso/resp/user_info.py
qiyu_sso/values.py
qiyu_sso-0.2.14.dist-info/LICENSE
qiyu_sso-0.2.14.dist-info/WHEEL
qiyu_sso-0.2.14.dist-info/METADATA
qiyu_sso-0.2.14.dist-info/RECORD
