Metadata-Version: 2.1
Name: qiyu-sso
Version: 0.2.14
Summary: SSO client from QiYuTech
Author: dev
Author-email: dev@qiyutech.tech
Requires-Python: >=3.9,<3.11
Classifier: Programming Language :: Python :: 3
Classifier: Programming Language :: Python :: 3.9
Classifier: Programming Language :: Python :: 3.10
Requires-Dist: aiohttp (>=3,<4)
Requires-Dist: pydantic (>=1.9,<2)
Requires-Dist: requests (>=2,<3)
